octosuite/__init__.py
octosuite/app.py
octosuite/lib.py
octosuite/core/__init__.py
octosuite/core/cache.py
octosuite/core/github.py
octosuite/core/models.py
octosuite/tui/__init__.py
octosuite/tui/dialogs.py
octosuite/tui/menus.py
octosuite/tui/prompts.py
octosuite-4.0.0.dist-info/licenses/LICENSE
octosuite-4.0.0.dist-info/METADATA
octosuite-4.0.0.dist-info/WHEEL
octosuite-4.0.0.dist-info/entry_points.txt
octosuite-4.0.0.dist-info/top_level.txt
octosuite-4.0.0.dist-info/RECORD
