Metadata-Version: 2.4
Name: octosuite
Version: 4.0.0
Summary: TUI-based toolkit for GitHub data analysis.
Author-email: Ritchie Mwewa <hi@rly0nheart.com>
License-Expression: MIT
Project-URL: homepage, https://bellingcat.com
Project-URL: issues, https://github.com/bellingcat/octosuite/issues
Project-URL: repository, https://github.com/bellingcat/octosuite
Classifier: Development Status :: 5 - Production/Stable
Classifier: Programming Language :: Python :: 3
Classifier: Intended Audience :: End Users/Desktop
Classifier: Operating System :: OS Independent
Classifier: Natural Language :: English
Requires-Python: >=3.13
License-File: LICENSE
Requires-Dist: rich>=14.2.0
Requires-Dist: questionary>=2.1.1
Requires-Dist: pyfiglet>=1.0.4
Requires-Dist: update-checker>=0.18.0
Requires-Dist: black>=25.12.0
Provides-Extra: dev
Requires-Dist: black>=25.12.0; extra == "dev"
Dynamic: license-file
